Metadata-Version: 1.1
Name: django-array-field-select
Version: 0.2.0
Summary: A replacement for Django's ArrayField with a multiple select form field.
Home-page: https://github.com/silverlogic/django-array-field-select
Author: Ryan Pineo
Author-email: ryanpineo@gmail.com
License: MIT
Platform: UNKNOWN
Classifier: Framework :: Django
Classifier: Programming Language :: Python :: 2
Classifier: Programming Language :: Python :: 3
